django_echarts/__init__.py
django_echarts/ajax_echarts.py
django_echarts/class_typing.py
django_echarts/conf.py
django_echarts/custom_maps.py
django_echarts/geojson.py
django_echarts/site_exts.py
django_echarts/views.py
django_echarts/contrib/__init__.py
django_echarts/contrib/bootstrap3/__init__.py
django_echarts/contrib/bootstrap3/config.py
django_echarts/contrib/bootstrap3/templates/about.html
django_echarts/contrib/bootstrap3/templates/base.html
django_echarts/contrib/bootstrap3/templates/blank.html
django_echarts/contrib/bootstrap3/templates/chart_collection.html
django_echarts/contrib/bootstrap3/templates/chart_parametric.html
django_echarts/contrib/bootstrap3/templates/chart_single.html
django_echarts/contrib/bootstrap3/templates/home.html
django_echarts/contrib/bootstrap3/templates/items_grid.html
django_echarts/contrib/bootstrap3/templates/items_list.html
django_echarts/contrib/bootstrap3/templates/list.html
django_echarts/contrib/bootstrap3/templates/list_with_paginator.html
django_echarts/contrib/bootstrap3/templates/message.html
django_echarts/contrib/bootstrap3/templates/settings.html
django_echarts/contrib/bootstrap3/templates/simple/page.html
django_echarts/contrib/bootstrap3/templates/widgets/chart_info.html
django_echarts/contrib/bootstrap3/templates/widgets/container.html
django_echarts/contrib/bootstrap3/templates/widgets/jumbotron.html
django_echarts/contrib/bootstrap3/templates/widgets/link_group.html
django_echarts/contrib/bootstrap3/templates/widgets/row_container.html
django_echarts/contrib/bootstrap3/templates/widgets/title.html
django_echarts/contrib/bootstrap3/templates/widgets/value_item.html
django_echarts/contrib/bootstrap5/__init__.py
django_echarts/contrib/bootstrap5/config.py
django_echarts/contrib/bootstrap5/templates/about.html
django_echarts/contrib/bootstrap5/templates/base.html
django_echarts/contrib/bootstrap5/templates/blank.html
django_echarts/contrib/bootstrap5/templates/chart_collection.html
django_echarts-0.6.0.dist-info/LICENSE
django_echarts-0.6.0.dist-info/METADATA
django_echarts-0.6.0.dist-info/WHEEL
django_echarts-0.6.0.dist-info/top_level.txt
django_echarts-0.6.0.dist-info/RECORD
